[
    {
        "hostname": "REMOTE-022",
        "ip": "28.1.9.9",
        "sshPortOpen": false,
        "ftpPortOpen": false,
        "smtpPortOpen": false,
        "httpPortOpen": false,
        "sqlPortOpen": false,
        "hasAdminRights": true,
        "cpuCores": 1,
        "isConnectedTo": false,
        "ramUsed": 1786.75,
        "maxRam": 65536,
        "organizationName": "",
        "purchasedByPlayer": true,
        "backdoorInstalled": false,
        "baseDifficulty": 1,
        "hackDifficulty": 1,
        "minDifficulty": 1,
        "moneyAvailable": 0,
        "moneyMax": 0,
        "numOpenPortsRequired": 5,
        "openPortCount": 0,
        "requiredHackingSkill": 1,
        "serverGrowth": 1,
        "path": [
            "REMOTE-022"
        ],
        "connections": [
            "home"
        ],
        "freeRam": 63749.25
    },
    {
        "hostname": "REMOTE-021",
        "ip": "81.1.8.5",
        "sshPortOpen": false,
        "ftpPortOpen": false,
        "smtpPortOpen": false,
        "httpPortOpen": false,
        "sqlPortOpen": false,
        "hasAdminRights": true,
        "cpuCores": 1,
        "isConnectedTo": false,
        "ramUsed": 0,
        "maxRam": 16384,
        "organizationName": "",
        "purchasedByPlayer": true,
        "backdoorInstalled": false,
        "baseDifficulty": 1,
        "hackDifficulty": 1,
        "minDifficulty": 1,
        "moneyAvailable": 0,
        "moneyMax": 0,
        "numOpenPortsRequired": 5,
        "openPortCount": 0,
        "requiredHackingSkill": 1,
        "serverGrowth": 1,
        "path": [
            "REMOTE-021"
        ],
        "connections": [
            "home"
        ],
        "freeRam": 16384
    },
    {
        "hostname": "REMOTE-020",
        "ip": "61.1.3.8",
        "sshPortOpen": false,
        "ftpPortOpen": false,
        "smtpPortOpen": false,
        "httpPortOpen": false,
        "sqlPortOpen": false,
        "hasAdminRights": true,
        "cpuCores": 1,
        "isConnectedTo": false,
        "ramUsed": 0,
        "maxRam": 8192,
        "organizationName": "",
        "purchasedByPlayer": true,
        "backdoorInstalled": false,
        "baseDifficulty": 1,
        "hackDifficulty": 1,
        "minDifficulty": 1,
        "moneyAvailable": 0,
        "moneyMax": 0,
        "numOpenPortsRequired": 5,
        "openPortCount": 0,
        "requiredHackingSkill": 1,
        "serverGrowth": 1,
        "path": [
            "REMOTE-020"
        ],
        "connections": [
            "home"
        ],
        "freeRam": 8192
    },
    {
        "hostname": "REMOTE-012",
        "ip": "20.4.0.0",
        "sshPortOpen": false,
        "ftpPortOpen": false,
        "smtpPortOpen": false,
        "httpPortOpen": false,
        "sqlPortOpen": false,
        "hasAdminRights": true,
        "cpuCores": 1,
        "isConnectedTo": false,
        "ramUsed": 0,
        "maxRam": 4096,
        "organizationName": "",
        "purchasedByPlayer": true,
        "backdoorInstalled": false,
        "baseDifficulty": 1,
        "hackDifficulty": 1,
        "minDifficulty": 1,
        "moneyAvailable": 0,
        "moneyMax": 0,
        "numOpenPortsRequired": 5,
        "openPortCount": 0,
        "requiredHackingSkill": 1,
        "serverGrowth": 1,
        "path": [
            "REMOTE-012"
        ],
        "connections": [
            "home"
        ],
        "freeRam": 4096
    },
    {
        "hostname": "REMOTE-011",
        "ip": "99.0.8.4",
        "sshPortOpen": false,
        "ftpPortOpen": false,
        "smtpPortOpen": false,
        "httpPortOpen": false,
        "sqlPortOpen": false,
        "hasAdminRights": true,
        "cpuCores": 1,
        "isConnectedTo": false,
        "ramUsed": 0,
        "maxRam": 8192,
        "organizationName": "",
        "purchasedByPlayer": true,
        "backdoorInstalled": false,
        "baseDifficulty": 1,
        "hackDifficulty": 1,
        "minDifficulty": 1,
        "moneyAvailable": 0,
        "moneyMax": 0,
        "numOpenPortsRequired": 5,
        "openPortCount": 0,
        "requiredHackingSkill": 1,
        "serverGrowth": 1,
        "path": [
            "REMOTE-011"
        ],
        "connections": [
            "home"
        ],
        "freeRam": 8192
    },
    {
        "hostname": "REMOTE-010",
        "ip": "72.5.0.8",
        "sshPortOpen": false,
        "ftpPortOpen": false,
        "smtpPortOpen": false,
        "httpPortOpen": false,
        "sqlPortOpen": false,
        "hasAdminRights": true,
        "cpuCores": 1,
        "isConnectedTo": false,
        "ramUsed": 0,
        "maxRam": 4096,
        "organizationName": "",
        "purchasedByPlayer": true,
        "backdoorInstalled": false,
        "baseDifficulty": 1,
        "hackDifficulty": 1,
        "minDifficulty": 1,
        "moneyAvailable": 0,
        "moneyMax": 0,
        "numOpenPortsRequired": 5,
        "openPortCount": 0,
        "requiredHackingSkill": 1,
        "serverGrowth": 1,
        "path": [
            "REMOTE-010"
        ],
        "connections": [
            "home"
        ],
        "freeRam": 4096
    },
    {
        "hostname": "REMOTE-002",
        "ip": "55.4.8.9",
        "sshPortOpen": false,
        "ftpPortOpen": false,
        "smtpPortOpen": false,
        "httpPortOpen": false,
        "sqlPortOpen": false,
        "hasAdminRights": true,
        "cpuCores": 1,
        "isConnectedTo": false,
        "ramUsed": 0,
        "maxRam": 4096,
        "organizationName": "",
        "purchasedByPlayer": true,
        "backdoorInstalled": false,
        "baseDifficulty": 1,
        "hackDifficulty": 1,
        "minDifficulty": 1,
        "moneyAvailable": 0,
        "moneyMax": 0,
        "numOpenPortsRequired": 5,
        "openPortCount": 0,
        "requiredHackingSkill": 1,
        "serverGrowth": 1,
        "path": [
            "REMOTE-002"
        ],
        "connections": [
            "home"
        ],
        "freeRam": 4096
    },
    {
        "hostname": "REMOTE-001",
        "ip": "95.6.6.5",
        "sshPortOpen": false,
        "ftpPortOpen": false,
        "smtpPortOpen": false,
        "httpPortOpen": false,
        "sqlPortOpen": false,
        "hasAdminRights": true,
        "cpuCores": 1,
        "isConnectedTo": false,
        "ramUsed": 0,
        "maxRam": 1024,
        "organizationName": "",
        "purchasedByPlayer": true,
        "backdoorInstalled": false,
        "baseDifficulty": 1,
        "hackDifficulty": 1,
        "minDifficulty": 1,
        "moneyAvailable": 0,
        "moneyMax": 0,
        "numOpenPortsRequired": 5,
        "openPortCount": 0,
        "requiredHackingSkill": 1,
        "serverGrowth": 1,
        "path": [
            "REMOTE-001"
        ],
        "connections": [
            "home"
        ],
        "freeRam": 1024
    },
    {
        "hostname": "REMOTE-000",
        "ip": "64.2.0.8",
        "sshPortOpen": false,
        "ftpPortOpen": false,
        "smtpPortOpen": false,
        "httpPortOpen": false,
        "sqlPortOpen": false,
        "hasAdminRights": true,
        "cpuCores": 1,
        "isConnectedTo": false,
        "ramUsed": 0,
        "maxRam": 128,
        "organizationName": "",
        "purchasedByPlayer": true,
        "backdoorInstalled": false,
        "baseDifficulty": 1,
        "hackDifficulty": 1,
        "minDifficulty": 1,
        "moneyAvailable": 0,
        "moneyMax": 0,
        "numOpenPortsRequired": 5,
        "openPortCount": 0,
        "requiredHackingSkill": 1,
        "serverGrowth": 1,
        "path": [
            "REMOTE-000"
        ],
        "connections": [
            "home"
        ],
        "freeRam": 128
    },
    {
        "hostname": "darkweb",
        "ip": "7.1.2.0",
        "sshPortOpen": true,
        "ftpPortOpen": true,
        "smtpPortOpen": true,
        "httpPortOpen": true,
        "sqlPortOpen": false,
        "hasAdminRights": false,
        "cpuCores": 1,
        "isConnectedTo": false,
        "ramUsed": 0,
        "maxRam": 0,
        "organizationName": "darkweb",
        "purchasedByPlayer": false,
        "backdoorInstalled": false,
        "baseDifficulty": 1,
        "hackDifficulty": 1,
        "minDifficulty": 1,
        "moneyAvailable": 0,
        "moneyMax": 0,
        "numOpenPortsRequired": 5,
        "openPortCount": 4,
        "requiredHackingSkill": 1,
        "serverGrowth": 1,
        "path": [
            "darkweb"
        ],
        "connections": [
            "home"
        ],
        "freeRam": 0
    },
    {
        "hostname": "iron-gym",
        "ip": "53.3.0.8",
        "sshPortOpen": true,
        "ftpPortOpen": false,
        "smtpPortOpen": false,
        "httpPortOpen": false,
        "sqlPortOpen": false,
        "hasAdminRights": true,
        "cpuCores": 1,
        "isConnectedTo": false,
        "ramUsed": 0,
        "maxRam": 32,
        "organizationName": "Iron Gym Network",
        "purchasedByPlayer": false,
        "backdoorInstalled": false,
        "baseDifficulty": 30,
        "hackDifficulty": 11.414,
        "minDifficulty": 10,
        "moneyAvailable": 0,
        "moneyMax": 56250000,
        "numOpenPortsRequired": 1,
        "openPortCount": 1,
        "requiredHackingSkill": 100,
        "serverGrowth": 20,
        "path": [
            "iron-gym"
        ],
        "connections": [
            "home",
            "max-hardware"
        ],
        "freeRam": 32,
        "numberOfGrowthThreadsNeededToMax": 23443,
        "numberOfGrowthThreadsNeededToMaxHomeComputer": 22064,
        "growthMs": 52412,
        "weakenMs": 65515
    },
    {
        "hostname": "max-hardware",
        "ip": "81.1.2.4",
        "sshPortOpen": true,
        "ftpPortOpen": false,
        "smtpPortOpen": false,
        "httpPortOpen": false,
        "sqlPortOpen": false,
        "hasAdminRights": true,
        "cpuCores": 1,
        "isConnectedTo": false,
        "ramUsed": 0,
        "maxRam": 32,
        "organizationName": "Max Hardware Store",
        "purchasedByPlayer": false,
        "backdoorInstalled": false,
        "baseDifficulty": 15,
        "hackDifficulty": 6.3,
        "minDifficulty": 5,
        "moneyAvailable": 0,
        "moneyMax": 28125000,
        "numOpenPortsRequired": 1,
        "openPortCount": 1,
        "requiredHackingSkill": 80,
        "serverGrowth": 30,
        "path": [
            "iron-gym",
            "max-hardware"
        ],
        "connections": [
            "iron-gym"
        ],
        "freeRam": 32,
        "numberOfGrowthThreadsNeededToMax": 11286,
        "numberOfGrowthThreadsNeededToMaxHomeComputer": 10622,
        "growthMs": 27507,
        "weakenMs": 34384
    },
    {
        "hostname": "harakiri-sushi",
        "ip": "54.0.8.3",
        "sshPortOpen": false,
        "ftpPortOpen": false,
        "smtpPortOpen": false,
        "httpPortOpen": false,
        "sqlPortOpen": false,
        "hasAdminRights": true,
        "cpuCores": 1,
        "isConnectedTo": false,
        "ramUsed": 0,
        "maxRam": 16,
        "organizationName": "HaraKiri Sushi Bar Network",
        "purchasedByPlayer": false,
        "backdoorInstalled": false,
        "baseDifficulty": 15,
        "hackDifficulty": 7.414000000000001,
        "minDifficulty": 5,
        "moneyAvailable": 4911388.7499763295,
        "moneyMax": 11250000,
        "numOpenPortsRequired": 0,
        "openPortCount": 0,
        "requiredHackingSkill": 40,
        "serverGrowth": 40,
        "path": [
            "harakiri-sushi"
        ],
        "connections": [
            "home"
        ],
        "freeRam": 16,
        "hackThreadsForAllMoney": 624,
        "hackChance": 1,
        "hackMs": 6064,
        "numberOfGrowthThreadsNeededToMax": 409,
        "numberOfGrowthThreadsNeededToMaxHomeComputer": 385,
        "growthMs": 19402,
        "weakenMs": 24253
    },
    {
        "hostname": "hong-fang-tea",
        "ip": "35.6.3.4",
        "sshPortOpen": false,
        "ftpPortOpen": false,
        "smtpPortOpen": false,
        "httpPortOpen": false,
        "sqlPortOpen": false,
        "hasAdminRights": true,
        "cpuCores": 1,
        "isConnectedTo": false,
        "ramUsed": 0,
        "maxRam": 16,
        "organizationName": "HongFang Teahouse",
        "purchasedByPlayer": false,
        "backdoorInstalled": false,
        "baseDifficulty": 15,
        "hackDifficulty": 5.35,
        "minDifficulty": 5,
        "moneyAvailable": 6066694.271046326,
        "moneyMax": 8437500,
        "numOpenPortsRequired": 0,
        "openPortCount": 0,
        "requiredHackingSkill": 30,
        "serverGrowth": 20,
        "path": [
            "hong-fang-tea"
        ],
        "connections": [
            "home"
        ],
        "freeRam": 16,
        "hackThreadsForAllMoney": 602,
        "hackChance": 1,
        "hackMs": 4402,
        "numberOfGrowthThreadsNeededToMax": 326,
        "numberOfGrowthThreadsNeededToMaxHomeComputer": 307,
        "growthMs": 14086,
        "weakenMs": 17607
    },
    {
        "hostname": "joesguns",
        "ip": "95.2.2.2",
        "sshPortOpen": false,
        "ftpPortOpen": false,
        "smtpPortOpen": false,
        "httpPortOpen": false,
        "sqlPortOpen": false,
        "hasAdminRights": true,
        "cpuCores": 1,
        "isConnectedTo": false,
        "ramUsed": 0,
        "maxRam": 16,
        "organizationName": "Joe's Guns",
        "purchasedByPlayer": false,
        "backdoorInstalled": false,
        "baseDifficulty": 15,
        "hackDifficulty": 6.164,
        "minDifficulty": 5,
        "moneyAvailable": 0,
        "moneyMax": 7031250,
        "numOpenPortsRequired": 0,
        "openPortCount": 0,
        "requiredHackingSkill": 10,
        "serverGrowth": 20,
        "path": [
            "joesguns"
        ],
        "connections": [
            "home",
            "nectar-net"
        ],
        "freeRam": 16,
        "numberOfGrowthThreadsNeededToMax": 15561,
        "numberOfGrowthThreadsNeededToMaxHomeComputer": 14645,
        "growthMs": 10223,
        "weakenMs": 12779
    },
    {
        "hostname": "nectar-net",
        "ip": "73.0.0.0",
        "sshPortOpen": false,
        "ftpPortOpen": false,
        "smtpPortOpen": false,
        "httpPortOpen": false,
        "sqlPortOpen": false,
        "hasAdminRights": true,
        "cpuCores": 1,
        "isConnectedTo": false,
        "ramUsed": 0,
        "maxRam": 16,
        "organizationName": "Nectar Nightclub Network",
        "purchasedByPlayer": false,
        "backdoorInstalled": false,
        "baseDifficulty": 20,
        "hackDifficulty": 12.918,
        "minDifficulty": 7,
        "moneyAvailable": 0,
        "moneyMax": 7734375,
        "numOpenPortsRequired": 0,
        "openPortCount": 0,
        "requiredHackingSkill": 20,
        "serverGrowth": 25,
        "path": [
            "joesguns",
            "nectar-net"
        ],
        "connections": [
            "joesguns"
        ],
        "freeRam": 16,
        "numberOfGrowthThreadsNeededToMax": 18863,
        "numberOfGrowthThreadsNeededToMaxHomeComputer": 17754,
        "growthMs": 17910,
        "weakenMs": 22387
    },
    {
        "hostname": "sigma-cosmetics",
        "ip": "91.0.0.3",
        "sshPortOpen": false,
        "ftpPortOpen": false,
        "smtpPortOpen": false,
        "httpPortOpen": false,
        "sqlPortOpen": false,
        "hasAdminRights": true,
        "cpuCores": 1,
        "isConnectedTo": false,
        "ramUsed": 0,
        "maxRam": 16,
        "organizationName": "Sigma Cosmetics",
        "purchasedByPlayer": false,
        "backdoorInstalled": false,
        "baseDifficulty": 10,
        "hackDifficulty": 4.132,
        "minDifficulty": 3,
        "moneyAvailable": 0,
        "moneyMax": 6468750,
        "numOpenPortsRequired": 0,
        "openPortCount": 0,
        "requiredHackingSkill": 5,
        "serverGrowth": 10,
        "path": [
            "sigma-cosmetics"
        ],
        "connections": [
            "home"
        ],
        "freeRam": 16,
        "numberOfGrowthThreadsNeededToMax": 30956,
        "numberOfGrowthThreadsNeededToMaxHomeComputer": 29135,
        "growthMs": 8622,
        "weakenMs": 10778
    },
    {
        "hostname": "foodnstuff",
        "ip": "60.7.3.1",
        "sshPortOpen": false,
        "ftpPortOpen": false,
        "smtpPortOpen": false,
        "httpPortOpen": false,
        "sqlPortOpen": false,
        "hasAdminRights": true,
        "cpuCores": 1,
        "isConnectedTo": false,
        "ramUsed": 0,
        "maxRam": 16,
        "organizationName": "FoodNStuff",
        "purchasedByPlayer": false,
        "backdoorInstalled": false,
        "baseDifficulty": 10,
        "hackDifficulty": 4.126,
        "minDifficulty": 3,
        "moneyAvailable": 0,
        "moneyMax": 5625000,
        "numOpenPortsRequired": 0,
        "openPortCount": 0,
        "requiredHackingSkill": 1,
        "serverGrowth": 5,
        "path": [
            "foodnstuff"
        ],
        "connections": [
            "home"
        ],
        "freeRam": 16,
        "numberOfGrowthThreadsNeededToMax": 61360,
        "numberOfGrowthThreadsNeededToMaxHomeComputer": 57750,
        "growthMs": 7976,
        "weakenMs": 9970
    },
    {
        "hostname": "n00dles",
        "ip": "83.2.2.6",
        "sshPortOpen": false,
        "ftpPortOpen": false,
        "smtpPortOpen": false,
        "httpPortOpen": false,
        "sqlPortOpen": false,
        "hasAdminRights": true,
        "cpuCores": 1,
        "isConnectedTo": false,
        "ramUsed": 0,
        "maxRam": 4,
        "organizationName": "Noodle Bar",
        "purchasedByPlayer": false,
        "backdoorInstalled": false,
        "baseDifficulty": 1,
        "hackDifficulty": 4.958,
        "minDifficulty": 1,
        "moneyAvailable": 0,
        "moneyMax": 196875,
        "numOpenPortsRequired": 0,
        "openPortCount": 0,
        "requiredHackingSkill": 1,
        "serverGrowth": 3000,
        "path": [
            "n00dles"
        ],
        "connections": [
            "home",
            "zer0",
            "CSEC"
        ],
        "freeRam": 4,
        "numberOfGrowthThreadsNeededToMax": 81,
        "numberOfGrowthThreadsNeededToMaxHomeComputer": 76,
        "growthMs": 8009,
        "weakenMs": 10011
    },
    {
        "hostname": "CSEC",
        "ip": "21.2.1.6",
        "sshPortOpen": true,
        "ftpPortOpen": false,
        "smtpPortOpen": false,
        "httpPortOpen": false,
        "sqlPortOpen": false,
        "hasAdminRights": true,
        "cpuCores": 1,
        "isConnectedTo": false,
        "ramUsed": 0,
        "maxRam": 8,
        "organizationName": "CyberSec",
        "purchasedByPlayer": false,
        "backdoorInstalled": true,
        "baseDifficulty": 1,
        "hackDifficulty": 1,
        "minDifficulty": 1,
        "moneyAvailable": 0,
        "moneyMax": 0,
        "numOpenPortsRequired": 1,
        "openPortCount": 1,
        "requiredHackingSkill": 57,
        "serverGrowth": 1,
        "path": [
            "n00dles",
            "CSEC"
        ],
        "connections": [
            "n00dles",
            "neo-net"
        ],
        "freeRam": 8
    },
    {
        "hostname": "neo-net",
        "ip": "22.5.6.5",
        "sshPortOpen": true,
        "ftpPortOpen": false,
        "smtpPortOpen": false,
        "httpPortOpen": false,
        "sqlPortOpen": false,
        "hasAdminRights": true,
        "cpuCores": 1,
        "isConnectedTo": false,
        "ramUsed": 0,
        "maxRam": 32,
        "organizationName": "Neo Nightclub Network",
        "purchasedByPlayer": false,
        "backdoorInstalled": false,
        "baseDifficulty": 25,
        "hackDifficulty": 9.278,
        "minDifficulty": 8,
        "moneyAvailable": 0,
        "moneyMax": 14062500,
        "numOpenPortsRequired": 1,
        "openPortCount": 1,
        "requiredHackingSkill": 50,
        "serverGrowth": 25,
        "path": [
            "n00dles",
            "CSEC",
            "neo-net"
        ],
        "connections": [
            "CSEC"
        ],
        "freeRam": 32,
        "numberOfGrowthThreadsNeededToMax": 14065,
        "numberOfGrowthThreadsNeededToMaxHomeComputer": 13238,
        "growthMs": 25940,
        "weakenMs": 32425
    },
    {
        "hostname": "zer0",
        "ip": "70.8.4.0",
        "sshPortOpen": true,
        "ftpPortOpen": false,
        "smtpPortOpen": false,
        "httpPortOpen": false,
        "sqlPortOpen": false,
        "hasAdminRights": true,
        "cpuCores": 1,
        "isConnectedTo": false,
        "ramUsed": 0,
        "maxRam": 32,
        "organizationName": "ZER0 Nightclub",
        "purchasedByPlayer": false,
        "backdoorInstalled": false,
        "baseDifficulty": 25,
        "hackDifficulty": 9.33,
        "minDifficulty": 8,
        "moneyAvailable": 0,
        "moneyMax": 21093750,
        "numOpenPortsRequired": 1,
        "openPortCount": 1,
        "requiredHackingSkill": 75,
        "serverGrowth": 40,
        "path": [
            "n00dles",
            "zer0"
        ],
        "connections": [
            "n00dles",
            "silver-helix",
            "phantasy",
            "omega-net"
        ],
        "freeRam": 32,
        "numberOfGrowthThreadsNeededToMax": 9058,
        "numberOfGrowthThreadsNeededToMaxHomeComputer": 8525,
        "growthMs": 35156,
        "weakenMs": 43944
    },
    {
        "hostname": "omega-net",
        "ip": "91.1.4.7",
        "sshPortOpen": true,
        "ftpPortOpen": true,
        "smtpPortOpen": false,
        "httpPortOpen": false,
        "sqlPortOpen": false,
        "hasAdminRights": true,
        "cpuCores": 1,
        "isConnectedTo": false,
        "ramUsed": 0,
        "maxRam": 32,
        "organizationName": "Omega Software",
        "purchasedByPlayer": false,
        "backdoorInstalled": false,
        "baseDifficulty": 32,
        "hackDifficulty": 12.756,
        "minDifficulty": 11,
        "moneyAvailable": 0,
        "moneyMax": 192782157.1875,
        "numOpenPortsRequired": 2,
        "openPortCount": 2,
        "requiredHackingSkill": 208,
        "serverGrowth": 33,
        "path": [
            "n00dles",
            "zer0",
            "omega-net"
        ],
        "connections": [
            "zer0",
            "computek",
            "johnson-ortho"
        ],
        "freeRam": 32,
        "numberOfGrowthThreadsNeededToMax": 16973,
        "numberOfGrowthThreadsNeededToMaxHomeComputer": 15974,
        "growthMs": 111483,
        "weakenMs": 139353
    },
    {
        "hostname": "johnson-ortho",
        "ip": "30.9.4.1",
        "sshPortOpen": true,
        "ftpPortOpen": true,
        "smtpPortOpen": false,
        "httpPortOpen": false,
        "sqlPortOpen": false,
        "hasAdminRights": true,
        "cpuCores": 1,
        "isConnectedTo": false,
        "ramUsed": 0,
        "maxRam": 0,
        "organizationName": "Johnson Orthopedics",
        "purchasedByPlayer": false,
        "backdoorInstalled": false,
        "baseDifficulty": 39,
        "hackDifficulty": 15.146,
        "minDifficulty": 13,
        "moneyAvailable": 0,
        "moneyMax": 213927921.5625,
        "numOpenPortsRequired": 2,
        "openPortCount": 2,
        "requiredHackingSkill": 290,
        "serverGrowth": 35,
        "path": [
            "n00dles",
            "zer0",
            "omega-net",
            "johnson-ortho"
        ],
        "connections": [
            "omega-net",
            "catalyst"
        ],
        "freeRam": 0,
        "numberOfGrowthThreadsNeededToMax": 19101,
        "numberOfGrowthThreadsNeededToMaxHomeComputer": 17977,
        "growthMs": 179433,
        "weakenMs": 224291
    },
    {
        "hostname": "catalyst",
        "ip": "87.2.4.7",
        "sshPortOpen": true,
        "ftpPortOpen": true,
        "smtpPortOpen": true,
        "httpPortOpen": false,
        "sqlPortOpen": false,
        "hasAdminRights": true,
        "cpuCores": 1,
        "isConnectedTo": false,
        "ramUsed": 0,
        "maxRam": 32,
        "organizationName": "Catalyst Ventures",
        "purchasedByPlayer": false,
        "backdoorInstalled": false,
        "baseDifficulty": 64,
        "hackDifficulty": 36.54000000000004,
        "minDifficulty": 21,
        "moneyAvailable": 75430.02708009513,
        "moneyMax": 1078938185.625,
        "numOpenPortsRequired": 3,
        "openPortCount": 3,
        "requiredHackingSkill": 440,
        "serverGrowth": 31,
        "path": [
            "n00dles",
            "zer0",
            "omega-net",
            "johnson-ortho",
            "catalyst"
        ],
        "connections": [
            "johnson-ortho"
        ],
        "freeRam": 32,
        "hackThreadsForAllMoney": 2327,
        "hackChance": 0.5184047399999996,
        "hackMs": 198750,
        "numberOfGrowthThreadsNeededToMax": 25938,
        "numberOfGrowthThreadsNeededToMaxHomeComputer": 24412,
        "growthMs": 636000,
        "weakenMs": 795000
    },
    {
        "hostname": "computek",
        "ip": "96.1.2.4",
        "sshPortOpen": true,
        "ftpPortOpen": true,
        "smtpPortOpen": true,
        "httpPortOpen": false,
        "sqlPortOpen": false,
        "hasAdminRights": true,
        "cpuCores": 1,
        "isConnectedTo": false,
        "ramUsed": 0,
        "maxRam": 0,
        "organizationName": "CompuTek",
        "purchasedByPlayer": false,
        "backdoorInstalled": false,
        "baseDifficulty": 64,
        "hackDifficulty": 74.736,
        "minDifficulty": 21,
        "moneyAvailable": 687453505.3125,
        "moneyMax": 687453505.3125,
        "numOpenPortsRequired": 3,
        "openPortCount": 3,
        "requiredHackingSkill": 333,
        "serverGrowth": 62,
        "path": [
            "n00dles",
            "zer0",
            "omega-net",
            "computek"
        ],
        "connections": [
            "omega-net",
            "zb-institute"
        ],
        "freeRam": 0,
        "hackThreadsForAllMoney": 4127,
        "hackChance": 0.23476571999999996,
        "hackMs": 306314,
        "numberOfGrowthThreadsNeededToMax": 0,
        "numberOfGrowthThreadsNeededToMaxHomeComputer": 0,
        "growthMs": 980205,
        "weakenMs": 1225256
    },
    {
        "hostname": "zb-institute",
        "ip": "22.2.9.2",
        "sshPortOpen": false,
        "ftpPortOpen": false,
        "smtpPortOpen": false,
        "httpPortOpen": false,
        "sqlPortOpen": false,
        "hasAdminRights": false,
        "cpuCores": 1,
        "isConnectedTo": false,
        "ramUsed": 0,
        "maxRam": 64,
        "organizationName": "ZB Institute of Technology",
        "purchasedByPlayer": false,
        "backdoorInstalled": false,
        "baseDifficulty": 67,
        "hackDifficulty": 67,
        "minDifficulty": 22,
        "moneyAvailable": 692354190,
        "moneyMax": 2596328212.5,
        "numOpenPortsRequired": 5,
        "openPortCount": 0,
        "requiredHackingSkill": 753,
        "serverGrowth": 82,
        "path": [
            "n00dles",
            "zer0",
            "omega-net",
            "computek",
            "zb-institute"
        ],
        "connections": [
            "computek"
        ],
        "freeRam": 64
    },
    {
        "hostname": "phantasy",
        "ip": "52.5.1.4",
        "sshPortOpen": true,
        "ftpPortOpen": true,
        "smtpPortOpen": false,
        "httpPortOpen": false,
        "sqlPortOpen": false,
        "hasAdminRights": true,
        "cpuCores": 1,
        "isConnectedTo": false,
        "ramUsed": 0,
        "maxRam": 32,
        "organizationName": "Phantasy Club",
        "purchasedByPlayer": false,
        "backdoorInstalled": false,
        "baseDifficulty": 20,
        "hackDifficulty": 9.831999999999999,
        "minDifficulty": 7,
        "moneyAvailable": 0,
        "moneyMax": 67500000,
        "numOpenPortsRequired": 2,
        "openPortCount": 2,
        "requiredHackingSkill": 100,
        "serverGrowth": 35,
        "path": [
            "n00dles",
            "zer0",
            "phantasy"
        ],
        "connections": [
            "zer0",
            "netlink"
        ],
        "freeRam": 32,
        "numberOfGrowthThreadsNeededToMax": 11660,
        "numberOfGrowthThreadsNeededToMaxHomeComputer": 10974,
        "growthMs": 46231,
        "weakenMs": 57788
    },
    {
        "hostname": "netlink",
        "ip": "21.3.3.0",
        "sshPortOpen": true,
        "ftpPortOpen": true,
        "smtpPortOpen": true,
        "httpPortOpen": false,
        "sqlPortOpen": false,
        "hasAdminRights": true,
        "cpuCores": 1,
        "isConnectedTo": false,
        "ramUsed": 0,
        "maxRam": 64,
        "organizationName": "NetLink Technologies",
        "purchasedByPlayer": false,
        "backdoorInstalled": false,
        "baseDifficulty": 73,
        "hackDifficulty": 28.74,
        "minDifficulty": 24,
        "moneyAvailable": 760821174.52077,
        "moneyMax": 773437500,
        "numOpenPortsRequired": 3,
        "openPortCount": 3,
        "requiredHackingSkill": 400,
        "serverGrowth": 63,
        "path": [
            "n00dles",
            "zer0",
            "phantasy",
            "netlink"
        ],
        "connections": [
            "phantasy",
            "summit-uni"
        ],
        "freeRam": 64,
        "hackThreadsForAllMoney": 1793,
        "hackChance": 0.61205214,
        "hackMs": 142809,
        "numberOfGrowthThreadsNeededToMax": 18,
        "numberOfGrowthThreadsNeededToMaxHomeComputer": 17,
        "growthMs": 456988,
        "weakenMs": 571234
    },
    {
        "hostname": "summit-uni",
        "ip": "0.9.4.2",
        "sshPortOpen": true,
        "ftpPortOpen": true,
        "smtpPortOpen": true,
        "httpPortOpen": false,
        "sqlPortOpen": false,
        "hasAdminRights": true,
        "cpuCores": 1,
        "isConnectedTo": false,
        "ramUsed": 0,
        "maxRam": 16,
        "organizationName": "Summit University",
        "purchasedByPlayer": false,
        "backdoorInstalled": false,
        "baseDifficulty": 54,
        "hackDifficulty": 50.92,
        "minDifficulty": 18,
        "moneyAvailable": 683199511.875,
        "moneyMax": 683199511.875,
        "numOpenPortsRequired": 3,
        "openPortCount": 3,
        "requiredHackingSkill": 472,
        "serverGrowth": 57,
        "path": [
            "n00dles",
            "zer0",
            "phantasy",
            "netlink",
            "summit-uni"
        ],
        "connections": [
            "netlink",
            "millenium-fitness"
        ],
        "freeRam": 16,
        "hackThreadsForAllMoney": 3437,
        "hackChance": 0.3844436399999999,
        "hackMs": 295901,
        "numberOfGrowthThreadsNeededToMax": 0,
        "numberOfGrowthThreadsNeededToMaxHomeComputer": 0,
        "growthMs": 946883,
        "weakenMs": 1183603
    },
    {
        "hostname": "millenium-fitness",
        "ip": "26.8.4.7",
        "sshPortOpen": true,
        "ftpPortOpen": true,
        "smtpPortOpen": true,
        "httpPortOpen": true,
        "sqlPortOpen": false,
        "hasAdminRights": true,
        "cpuCores": 1,
        "isConnectedTo": false,
        "ramUsed": 0,
        "maxRam": 256,
        "organizationName": "Millenium Fitness Network",
        "purchasedByPlayer": false,
        "backdoorInstalled": false,
        "baseDifficulty": 48,
        "hackDifficulty": 21.2,
        "minDifficulty": 16,
        "moneyAvailable": 0,
        "moneyMax": 703125000,
        "numOpenPortsRequired": 3,
        "openPortCount": 4,
        "requiredHackingSkill": 521,
        "serverGrowth": 39,
        "path": [
            "n00dles",
            "zer0",
            "phantasy",
            "netlink",
            "summit-uni",
            "millenium-fitness"
        ],
        "connections": [
            "summit-uni",
            "aerocorp"
        ],
        "freeRam": 256,
        "numberOfGrowthThreadsNeededToMax": 25475,
        "numberOfGrowthThreadsNeededToMaxHomeComputer": 23976,
        "growthMs": 439374,
        "weakenMs": 549217
    },
    {
        "hostname": "aerocorp",
        "ip": "32.3.0.9",
        "sshPortOpen": false,
        "ftpPortOpen": false,
        "smtpPortOpen": false,
        "httpPortOpen": false,
        "sqlPortOpen": false,
        "hasAdminRights": false,
        "cpuCores": 1,
        "isConnectedTo": false,
        "ramUsed": 0,
        "maxRam": 0,
        "organizationName": "AeroCorp",
        "purchasedByPlayer": false,
        "backdoorInstalled": false,
        "baseDifficulty": 89,
        "hackDifficulty": 89,
        "minDifficulty": 30,
        "moneyAvailable": 786236377.5,
        "moneyMax": 2948386415.625,
        "numOpenPortsRequired": 5,
        "openPortCount": 0,
        "requiredHackingSkill": 925,
        "serverGrowth": 61,
        "path": [
            "n00dles",
            "zer0",
            "phantasy",
            "netlink",
            "summit-uni",
            "millenium-fitness",
            "aerocorp"
        ],
        "connections": [
            "millenium-fitness",
            "deltaone"
        ],
        "freeRam": 0
    },
    {
        "hostname": "deltaone",
        "ip": "42.3.9.2",
        "sshPortOpen": false,
        "ftpPortOpen": false,
        "smtpPortOpen": false,
        "httpPortOpen": false,
        "sqlPortOpen": false,
        "hasAdminRights": false,
        "cpuCores": 1,
        "isConnectedTo": false,
        "ramUsed": 0,
        "maxRam": 0,
        "organizationName": "DeltaOne",
        "purchasedByPlayer": false,
        "backdoorInstalled": false,
        "baseDifficulty": 84,
        "hackDifficulty": 84,
        "minDifficulty": 28,
        "moneyAvailable": 1056262301.25,
        "moneyMax": 3960983629.6875,
        "numOpenPortsRequired": 5,
        "openPortCount": 0,
        "requiredHackingSkill": 862,
        "serverGrowth": 61,
        "path": [
            "n00dles",
            "zer0",
            "phantasy",
            "netlink",
            "summit-uni",
            "millenium-fitness",
            "aerocorp",
            "deltaone"
        ],
        "connections": [
            "aerocorp",
            "defcomm",
            "univ-energy",
            "solaris",
            "zeus-med"
        ],
        "freeRam": 0
    },
    {
        "hostname": "zeus-med",
        "ip": "70.9.8.2",
        "sshPortOpen": false,
        "ftpPortOpen": false,
        "smtpPortOpen": false,
        "httpPortOpen": false,
        "sqlPortOpen": false,
        "hasAdminRights": false,
        "cpuCores": 1,
        "isConnectedTo": false,
        "ramUsed": 0,
        "maxRam": 0,
        "organizationName": "Zeus Medical",
        "purchasedByPlayer": false,
        "backdoorInstalled": false,
        "baseDifficulty": 88,
        "hackDifficulty": 88,
        "minDifficulty": 29,
        "moneyAvailable": 1092430567.5,
        "moneyMax": 4096614628.125,
        "numOpenPortsRequired": 5,
        "openPortCount": 0,
        "requiredHackingSkill": 850,
        "serverGrowth": 75,
        "path": [
            "n00dles",
            "zer0",
            "phantasy",
            "netlink",
            "summit-uni",
            "millenium-fitness",
            "aerocorp",
            "deltaone",
            "zeus-med"
        ],
        "connections": [
            "deltaone",
            "taiyang-digital",
            "nova-med"
        ],
        "freeRam": 0
    },
    {
        "hostname": "nova-med",
        "ip": "78.5.0.5",
        "sshPortOpen": false,
        "ftpPortOpen": false,
        "smtpPortOpen": false,
        "httpPortOpen": false,
        "sqlPortOpen": false,
        "hasAdminRights": false,
        "cpuCores": 1,
        "isConnectedTo": false,
        "ramUsed": 0,
        "maxRam": 0,
        "organizationName": "Nova Medical",
        "purchasedByPlayer": false,
        "backdoorInstalled": false,
        "baseDifficulty": 76,
        "hackDifficulty": 76,
        "minDifficulty": 25,
        "moneyAvailable": 825069807.75,
        "moneyMax": 3094011779.0625,
        "numOpenPortsRequired": 4,
        "openPortCount": 0,
        "requiredHackingSkill": 789,
        "serverGrowth": 83,
        "path": [
            "n00dles",
            "zer0",
            "phantasy",
            "netlink",
            "summit-uni",
            "millenium-fitness",
            "aerocorp",
            "deltaone",
            "zeus-med",
            "nova-med"
        ],
        "connections": [
            "zeus-med",
            "titan-labs"
        ],
        "freeRam": 0
    },
    {
        "hostname": "titan-labs",
        "ip": "48.7.5.5",
        "sshPortOpen": false,
        "ftpPortOpen": false,
        "smtpPortOpen": false,
        "httpPortOpen": false,
        "sqlPortOpen": false,
        "hasAdminRights": false,
        "cpuCores": 1,
        "isConnectedTo": false,
        "ramUsed": 0,
        "maxRam": 16,
        "organizationName": "Titan Laboratories",
        "purchasedByPlayer": false,
        "backdoorInstalled": false,
        "baseDifficulty": 78,
        "hackDifficulty": 78,
        "minDifficulty": 26,
        "moneyAvailable": 630277468.5,
        "moneyMax": 2363540506.875,
        "numOpenPortsRequired": 5,
        "openPortCount": 0,
        "requiredHackingSkill": 818,
        "serverGrowth": 60,
        "path": [
            "n00dles",
            "zer0",
            "phantasy",
            "netlink",
            "summit-uni",
            "millenium-fitness",
            "aerocorp",
            "deltaone",
            "zeus-med",
            "nova-med",
            "titan-labs"
        ],
        "connections": [
            "nova-med",
            "stormtech"
        ],
        "freeRam": 16
    },
    {
        "hostname": "stormtech",
        "ip": "3.6.3.8",
        "sshPortOpen": false,
        "ftpPortOpen": false,
        "smtpPortOpen": false,
        "httpPortOpen": false,
        "sqlPortOpen": false,
        "hasAdminRights": false,
        "cpuCores": 1,
        "isConnectedTo": false,
        "ramUsed": 0,
        "maxRam": 0,
        "organizationName": "Storm Technologies",
        "purchasedByPlayer": false,
        "backdoorInstalled": false,
        "baseDifficulty": 92,
        "hackDifficulty": 92,
        "minDifficulty": 31,
        "moneyAvailable": 766141428.75,
        "moneyMax": 2873030357.8125,
        "numOpenPortsRequired": 5,
        "openPortCount": 0,
        "requiredHackingSkill": 977,
        "serverGrowth": 83,
        "path": [
            "n00dles",
            "zer0",
            "phantasy",
            "netlink",
            "summit-uni",
            "millenium-fitness",
            "aerocorp",
            "deltaone",
            "zeus-med",
            "nova-med",
            "titan-labs",
            "stormtech"
        ],
        "connections": [
            "titan-labs",
            "omnitek",
            "kuai-gong",
            "."
        ],
        "freeRam": 0
    },
    {
        "hostname": ".",
        "ip": "88.3.0.9",
        "sshPortOpen": true,
        "ftpPortOpen": true,
        "smtpPortOpen": true,
        "httpPortOpen": true,
        "sqlPortOpen": false,
        "hasAdminRights": true,
        "cpuCores": 1,
        "isConnectedTo": false,
        "ramUsed": 0,
        "maxRam": 16,
        "organizationName": ".",
        "purchasedByPlayer": false,
        "backdoorInstalled": false,
        "baseDifficulty": 1,
        "hackDifficulty": 1,
        "minDifficulty": 1,
        "moneyAvailable": 0,
        "moneyMax": 0,
        "numOpenPortsRequired": 4,
        "openPortCount": 4,
        "requiredHackingSkill": 533,
        "serverGrowth": 1,
        "path": [
            "n00dles",
            "zer0",
            "phantasy",
            "netlink",
            "summit-uni",
            "millenium-fitness",
            "aerocorp",
            "deltaone",
            "zeus-med",
            "nova-med",
            "titan-labs",
            "stormtech",
            "."
        ],
        "connections": [
            "stormtech",
            "b-and-a"
        ],
        "freeRam": 16
    },
    {
        "hostname": "b-and-a",
        "ip": "98.9.7.5",
        "sshPortOpen": false,
        "ftpPortOpen": false,
        "smtpPortOpen": false,
        "httpPortOpen": false,
        "sqlPortOpen": false,
        "hasAdminRights": false,
        "cpuCores": 1,
        "isConnectedTo": false,
        "ramUsed": 0,
        "maxRam": 0,
        "organizationName": "Bachman & Associates",
        "purchasedByPlayer": false,
        "backdoorInstalled": false,
        "baseDifficulty": 76,
        "hackDifficulty": 76,
        "minDifficulty": 25,
        "moneyAvailable": 21633318153,
        "moneyMax": 81124943073.75,
        "numOpenPortsRequired": 5,
        "openPortCount": 0,
        "requiredHackingSkill": 998,
        "serverGrowth": 72,
        "path": [
            "n00dles",
            "zer0",
            "phantasy",
            "netlink",
            "summit-uni",
            "millenium-fitness",
            "aerocorp",
            "deltaone",
            "zeus-med",
            "nova-med",
            "titan-labs",
            "stormtech",
            ".",
            "b-and-a"
        ],
        "connections": [
            ".",
            "ecorp",
            "fulcrumassets"
        ],
        "freeRam": 0
    },
    {
        "hostname": "fulcrumassets",
        "ip": "33.3.0.6",
        "sshPortOpen": false,
        "ftpPortOpen": false,
        "smtpPortOpen": false,
        "httpPortOpen": false,
        "sqlPortOpen": false,
        "hasAdminRights": false,
        "cpuCores": 1,
        "isConnectedTo": false,
        "ramUsed": 0,
        "maxRam": 0,
        "organizationName": "Fulcrum Technologies",
        "purchasedByPlayer": false,
        "backdoorInstalled": false,
        "baseDifficulty": 99,
        "hackDifficulty": 99,
        "minDifficulty": 33,
        "moneyAvailable": 750000,
        "moneyMax": 2812500,
        "numOpenPortsRequired": 5,
        "openPortCount": 0,
        "requiredHackingSkill": 1191,
        "serverGrowth": 1,
        "path": [
            "n00dles",
            "zer0",
            "phantasy",
            "netlink",
            "summit-uni",
            "millenium-fitness",
            "aerocorp",
            "deltaone",
            "zeus-med",
            "nova-med",
            "titan-labs",
            "stormtech",
            ".",
            "b-and-a",
            "fulcrumassets"
        ],
        "connections": [
            "b-and-a"
        ],
        "freeRam": 0
    },
    {
        "hostname": "ecorp",
        "ip": "70.1.7.1",
        "sshPortOpen": false,
        "ftpPortOpen": false,
        "smtpPortOpen": false,
        "httpPortOpen": false,
        "sqlPortOpen": false,
        "hasAdminRights": false,
        "cpuCores": 1,
        "isConnectedTo": false,
        "ramUsed": 0,
        "maxRam": 0,
        "organizationName": "ECorp",
        "purchasedByPlayer": false,
        "backdoorInstalled": false,
        "baseDifficulty": 99,
        "hackDifficulty": 99,
        "minDifficulty": 33,
        "moneyAvailable": 23442651045,
        "moneyMax": 87909941418.75,
        "numOpenPortsRequired": 5,
        "openPortCount": 0,
        "requiredHackingSkill": 1320,
        "serverGrowth": 99,
        "path": [
            "n00dles",
            "zer0",
            "phantasy",
            "netlink",
            "summit-uni",
            "millenium-fitness",
            "aerocorp",
            "deltaone",
            "zeus-med",
            "nova-med",
            "titan-labs",
            "stormtech",
            ".",
            "b-and-a",
            "ecorp"
        ],
        "connections": [
            "b-and-a"
        ],
        "freeRam": 0
    },
    {
        "hostname": "kuai-gong",
        "ip": "26.7.3.5",
        "sshPortOpen": false,
        "ftpPortOpen": false,
        "smtpPortOpen": false,
        "httpPortOpen": false,
        "sqlPortOpen": false,
        "hasAdminRights": false,
        "cpuCores": 1,
        "isConnectedTo": false,
        "ramUsed": 0,
        "maxRam": 0,
        "organizationName": "KuaiGong International",
        "purchasedByPlayer": false,
        "backdoorInstalled": false,
        "baseDifficulty": 98,
        "hackDifficulty": 98,
        "minDifficulty": 33,
        "moneyAvailable": 18467164752.75,
        "moneyMax": 69251867822.8125,
        "numOpenPortsRequired": 5,
        "openPortCount": 0,
        "requiredHackingSkill": 1217,
        "serverGrowth": 92,
        "path": [
            "n00dles",
            "zer0",
            "phantasy",
            "netlink",
            "summit-uni",
            "millenium-fitness",
            "aerocorp",
            "deltaone",
            "zeus-med",
            "nova-med",
            "titan-labs",
            "stormtech",
            "kuai-gong"
        ],
        "connections": [
            "stormtech",
            "nwo",
            "clarkinc"
        ],
        "freeRam": 0
    },
    {
        "hostname": "clarkinc",
        "ip": "83.4.2.7",
        "sshPortOpen": false,
        "ftpPortOpen": false,
        "smtpPortOpen": false,
        "httpPortOpen": false,
        "sqlPortOpen": false,
        "hasAdminRights": false,
        "cpuCores": 1,
        "isConnectedTo": false,
        "ramUsed": 0,
        "maxRam": 0,
        "organizationName": "Clarke Incorporated",
        "purchasedByPlayer": false,
        "backdoorInstalled": false,
        "baseDifficulty": 59,
        "hackDifficulty": 59,
        "minDifficulty": 20,
        "moneyAvailable": 13619582521.5,
        "moneyMax": 51073434455.625,
        "numOpenPortsRequired": 5,
        "openPortCount": 0,
        "requiredHackingSkill": 1085,
        "serverGrowth": 63,
        "path": [
            "n00dles",
            "zer0",
            "phantasy",
            "netlink",
            "summit-uni",
            "millenium-fitness",
            "aerocorp",
            "deltaone",
            "zeus-med",
            "nova-med",
            "titan-labs",
            "stormtech",
            "kuai-gong",
            "clarkinc"
        ],
        "connections": [
            "kuai-gong",
            "The-Cave"
        ],
        "freeRam": 0
    },
    {
        "hostname": "The-Cave",
        "ip": "16.5.7.1",
        "sshPortOpen": false,
        "ftpPortOpen": false,
        "smtpPortOpen": false,
        "httpPortOpen": false,
        "sqlPortOpen": false,
        "hasAdminRights": false,
        "cpuCores": 1,
        "isConnectedTo": false,
        "ramUsed": 0,
        "maxRam": 0,
        "organizationName": "Helios",
        "purchasedByPlayer": false,
        "backdoorInstalled": false,
        "baseDifficulty": 1,
        "hackDifficulty": 1,
        "minDifficulty": 1,
        "moneyAvailable": 0,
        "moneyMax": 0,
        "numOpenPortsRequired": 5,
        "openPortCount": 0,
        "requiredHackingSkill": 925,
        "serverGrowth": 1,
        "path": [
            "n00dles",
            "zer0",
            "phantasy",
            "netlink",
            "summit-uni",
            "millenium-fitness",
            "aerocorp",
            "deltaone",
            "zeus-med",
            "nova-med",
            "titan-labs",
            "stormtech",
            "kuai-gong",
            "clarkinc",
            "The-Cave"
        ],
        "connections": [
            "clarkinc"
        ],
        "freeRam": 0
    },
    {
        "hostname": "nwo",
        "ip": "0.3.3.2",
        "sshPortOpen": false,
        "ftpPortOpen": false,
        "smtpPortOpen": false,
        "httpPortOpen": false,
        "sqlPortOpen": false,
        "hasAdminRights": false,
        "cpuCores": 1,
        "isConnectedTo": false,
        "ramUsed": 0,
        "maxRam": 0,
        "organizationName": "NWO",
        "purchasedByPlayer": false,
        "backdoorInstalled": false,
        "baseDifficulty": 99,
        "hackDifficulty": 99,
        "minDifficulty": 33,
        "moneyAvailable": 24253579510.5,
        "moneyMax": 90950923164.375,
        "numOpenPortsRequired": 5,
        "openPortCount": 0,
        "requiredHackingSkill": 1027,
        "serverGrowth": 95,
        "path": [
            "n00dles",
            "zer0",
            "phantasy",
            "netlink",
            "summit-uni",
            "millenium-fitness",
            "aerocorp",
            "deltaone",
            "zeus-med",
            "nova-med",
            "titan-labs",
            "stormtech",
            "kuai-gong",
            "nwo"
        ],
        "connections": [
            "kuai-gong"
        ],
        "freeRam": 0
    },
    {
        "hostname": "omnitek",
        "ip": "67.4.4.2",
        "sshPortOpen": false,
        "ftpPortOpen": false,
        "smtpPortOpen": false,
        "httpPortOpen": false,
        "sqlPortOpen": false,
        "hasAdminRights": false,
        "cpuCores": 1,
        "isConnectedTo": false,
        "ramUsed": 0,
        "maxRam": 256,
        "organizationName": "OmniTek Incorporated",
        "purchasedByPlayer": false,
        "backdoorInstalled": false,
        "baseDifficulty": 92,
        "hackDifficulty": 92,
        "minDifficulty": 31,
        "moneyAvailable": 12081089958.75,
        "moneyMax": 45304087345.3125,
        "numOpenPortsRequired": 5,
        "openPortCount": 0,
        "requiredHackingSkill": 995,
        "serverGrowth": 99,
        "path": [
            "n00dles",
            "zer0",
            "phantasy",
            "netlink",
            "summit-uni",
            "millenium-fitness",
            "aerocorp",
            "deltaone",
            "zeus-med",
            "nova-med",
            "titan-labs",
            "stormtech",
            "omnitek"
        ],
        "connections": [
            "stormtech"
        ],
        "freeRam": 256
    },
    {
        "hostname": "taiyang-digital",
        "ip": "13.3.6.2",
        "sshPortOpen": false,
        "ftpPortOpen": false,
        "smtpPortOpen": false,
        "httpPortOpen": false,
        "sqlPortOpen": false,
        "hasAdminRights": false,
        "cpuCores": 1,
        "isConnectedTo": false,
        "ramUsed": 0,
        "maxRam": 0,
        "organizationName": "Taiyang Digital",
        "purchasedByPlayer": false,
        "backdoorInstalled": false,
        "baseDifficulty": 76,
        "hackDifficulty": 76,
        "minDifficulty": 25,
        "moneyAvailable": 645350586,
        "moneyMax": 2420064697.5,
        "numOpenPortsRequired": 5,
        "openPortCount": 0,
        "requiredHackingSkill": 906,
        "serverGrowth": 70,
        "path": [
            "n00dles",
            "zer0",
            "phantasy",
            "netlink",
            "summit-uni",
            "millenium-fitness",
            "aerocorp",
            "deltaone",
            "zeus-med",
            "taiyang-digital"
        ],
        "connections": [
            "zeus-med"
        ],
        "freeRam": 0
    },
    {
        "hostname": "solaris",
        "ip": "83.2.9.6",
        "sshPortOpen": false,
        "ftpPortOpen": false,
        "smtpPortOpen": false,
        "httpPortOpen": false,
        "sqlPortOpen": false,
        "hasAdminRights": false,
        "cpuCores": 1,
        "isConnectedTo": false,
        "ramUsed": 0,
        "maxRam": 32,
        "organizationName": "Solaris Space Systems",
        "purchasedByPlayer": false,
        "backdoorInstalled": false,
        "baseDifficulty": 76,
        "hackDifficulty": 76,
        "minDifficulty": 25,
        "moneyAvailable": 607226451,
        "moneyMax": 2277099191.25,
        "numOpenPortsRequired": 5,
        "openPortCount": 0,
        "requiredHackingSkill": 796,
        "serverGrowth": 78,
        "path": [
            "n00dles",
            "zer0",
            "phantasy",
            "netlink",
            "summit-uni",
            "millenium-fitness",
            "aerocorp",
            "deltaone",
            "solaris"
        ],
        "connections": [
            "deltaone"
        ],
        "freeRam": 32
    },
    {
        "hostname": "univ-energy",
        "ip": "20.7.8.3",
        "sshPortOpen": false,
        "ftpPortOpen": false,
        "smtpPortOpen": false,
        "httpPortOpen": false,
        "sqlPortOpen": false,
        "hasAdminRights": false,
        "cpuCores": 1,
        "isConnectedTo": false,
        "ramUsed": 0,
        "maxRam": 128,
        "organizationName": "Universal Energy",
        "purchasedByPlayer": false,
        "backdoorInstalled": false,
        "baseDifficulty": 86,
        "hackDifficulty": 86,
        "minDifficulty": 29,
        "moneyAvailable": 873065362.5,
        "moneyMax": 3273995109.375,
        "numOpenPortsRequired": 4,
        "openPortCount": 0,
        "requiredHackingSkill": 875,
        "serverGrowth": 80,
        "path": [
            "n00dles",
            "zer0",
            "phantasy",
            "netlink",
            "summit-uni",
            "millenium-fitness",
            "aerocorp",
            "deltaone",
            "univ-energy"
        ],
        "connections": [
            "deltaone"
        ],
        "freeRam": 128
    },
    {
        "hostname": "defcomm",
        "ip": "1.8.3.2",
        "sshPortOpen": false,
        "ftpPortOpen": false,
        "smtpPortOpen": false,
        "httpPortOpen": false,
        "sqlPortOpen": false,
        "hasAdminRights": false,
        "cpuCores": 1,
        "isConnectedTo": false,
        "ramUsed": 0,
        "maxRam": 0,
        "organizationName": "DefComm",
        "purchasedByPlayer": false,
        "backdoorInstalled": false,
        "baseDifficulty": 84,
        "hackDifficulty": 84,
        "minDifficulty": 28,
        "moneyAvailable": 656689328.25,
        "moneyMax": 2462584980.9375,
        "numOpenPortsRequired": 5,
        "openPortCount": 0,
        "requiredHackingSkill": 899,
        "serverGrowth": 54,
        "path": [
            "n00dles",
            "zer0",
            "phantasy",
            "netlink",
            "summit-uni",
            "millenium-fitness",
            "aerocorp",
            "deltaone",
            "defcomm"
        ],
        "connections": [
            "deltaone",
            "zb-def"
        ],
        "freeRam": 0
    },
    {
        "hostname": "zb-def",
        "ip": "99.9.1.2",
        "sshPortOpen": false,
        "ftpPortOpen": false,
        "smtpPortOpen": false,
        "httpPortOpen": false,
        "sqlPortOpen": false,
        "hasAdminRights": false,
        "cpuCores": 1,
        "isConnectedTo": false,
        "ramUsed": 0,
        "maxRam": 0,
        "organizationName": "ZB Defense Industries",
        "purchasedByPlayer": false,
        "backdoorInstalled": false,
        "baseDifficulty": 60,
        "hackDifficulty": 60,
        "minDifficulty": 20,
        "moneyAvailable": 760537311,
        "moneyMax": 2852014916.25,
        "numOpenPortsRequired": 4,
        "openPortCount": 0,
        "requiredHackingSkill": 781,
        "serverGrowth": 72,
        "path": [
            "n00dles",
            "zer0",
            "phantasy",
            "netlink",
            "summit-uni",
            "millenium-fitness",
            "aerocorp",
            "deltaone",
            "defcomm",
            "zb-def"
        ],
        "connections": [
            "defcomm",
            "microdyne"
        ],
        "freeRam": 0
    },
    {
        "hostname": "microdyne",
        "ip": "58.2.8.1",
        "sshPortOpen": false,
        "ftpPortOpen": false,
        "smtpPortOpen": false,
        "httpPortOpen": false,
        "sqlPortOpen": false,
        "hasAdminRights": false,
        "cpuCores": 1,
        "isConnectedTo": false,
        "ramUsed": 0,
        "maxRam": 64,
        "organizationName": "Microdyne Technologies",
        "purchasedByPlayer": false,
        "backdoorInstalled": false,
        "baseDifficulty": 67,
        "hackDifficulty": 67,
        "minDifficulty": 22,
        "moneyAvailable": 455775122.25,
        "moneyMax": 1709156708.4375,
        "numOpenPortsRequired": 5,
        "openPortCount": 0,
        "requiredHackingSkill": 864,
        "serverGrowth": 81,
        "path": [
            "n00dles",
            "zer0",
            "phantasy",
            "netlink",
            "summit-uni",
            "millenium-fitness",
            "aerocorp",
            "deltaone",
            "defcomm",
            "zb-def",
            "microdyne"
        ],
        "connections": [
            "zb-def"
        ],
        "freeRam": 64
    },
    {
        "hostname": "silver-helix",
        "ip": "83.0.9.2",
        "sshPortOpen": true,
        "ftpPortOpen": true,
        "smtpPortOpen": false,
        "httpPortOpen": false,
        "sqlPortOpen": false,
        "hasAdminRights": true,
        "cpuCores": 1,
        "isConnectedTo": false,
        "ramUsed": 0,
        "maxRam": 64,
        "organizationName": "Silver Helix",
        "purchasedByPlayer": false,
        "backdoorInstalled": false,
        "baseDifficulty": 30,
        "hackDifficulty": 11.544,
        "minDifficulty": 10,
        "moneyAvailable": 0,
        "moneyMax": 126562500,
        "numOpenPortsRequired": 2,
        "openPortCount": 2,
        "requiredHackingSkill": 150,
        "serverGrowth": 30,
        "path": [
            "n00dles",
            "zer0",
            "silver-helix"
        ],
        "connections": [
            "zer0",
            "the-hub",
            "crush-fitness",
            "avmnite-02h"
        ],
        "freeRam": 64,
        "numberOfGrowthThreadsNeededToMax": 16525,
        "numberOfGrowthThreadsNeededToMaxHomeComputer": 15553,
        "growthMs": 75472,
        "weakenMs": 94340
    },
    {
        "hostname": "avmnite-02h",
        "ip": "65.2.9.2",
        "sshPortOpen": true,
        "ftpPortOpen": true,
        "smtpPortOpen": false,
        "httpPortOpen": false,
        "sqlPortOpen": false,
        "hasAdminRights": true,
        "cpuCores": 1,
        "isConnectedTo": false,
        "ramUsed": 0,
        "maxRam": 16,
        "organizationName": "NiteSec",
        "purchasedByPlayer": false,
        "backdoorInstalled": true,
        "baseDifficulty": 1,
        "hackDifficulty": 1,
        "minDifficulty": 1,
        "moneyAvailable": 0,
        "moneyMax": 0,
        "numOpenPortsRequired": 2,
        "openPortCount": 2,
        "requiredHackingSkill": 219,
        "serverGrowth": 1,
        "path": [
            "n00dles",
            "zer0",
            "silver-helix",
            "avmnite-02h"
        ],
        "connections": [
            "silver-helix",
            "syscore",
            "I.I.I.I"
        ],
        "freeRam": 16
    },
    {
        "hostname": "I.I.I.I",
        "ip": "14.5.2.9",
        "sshPortOpen": true,
        "ftpPortOpen": true,
        "smtpPortOpen": true,
        "httpPortOpen": false,
        "sqlPortOpen": false,
        "hasAdminRights": true,
        "cpuCores": 1,
        "isConnectedTo": false,
        "ramUsed": 0,
        "maxRam": 256,
        "organizationName": "I.I.I.I",
        "purchasedByPlayer": false,
        "backdoorInstalled": true,
        "baseDifficulty": 1,
        "hackDifficulty": 1,
        "minDifficulty": 1,
        "moneyAvailable": 0,
        "moneyMax": 0,
        "numOpenPortsRequired": 3,
        "openPortCount": 3,
        "requiredHackingSkill": 355,
        "serverGrowth": 1,
        "path": [
            "n00dles",
            "zer0",
            "silver-helix",
            "avmnite-02h",
            "I.I.I.I"
        ],
        "connections": [
            "avmnite-02h",
            "alpha-ent"
        ],
        "freeRam": 256
    },
    {
        "hostname": "alpha-ent",
        "ip": "11.5.1.3",
        "sshPortOpen": true,
        "ftpPortOpen": true,
        "smtpPortOpen": true,
        "httpPortOpen": true,
        "sqlPortOpen": false,
        "hasAdminRights": true,
        "cpuCores": 1,
        "isConnectedTo": false,
        "ramUsed": 0,
        "maxRam": 32,
        "organizationName": "Alpha Enterprises",
        "purchasedByPlayer": false,
        "backdoorInstalled": false,
        "baseDifficulty": 66,
        "hackDifficulty": 29.012,
        "minDifficulty": 22,
        "moneyAvailable": 0,
        "moneyMax": 1929504726.5625,
        "numOpenPortsRequired": 4,
        "openPortCount": 4,
        "requiredHackingSkill": 539,
        "serverGrowth": 56,
        "path": [
            "n00dles",
            "zer0",
            "silver-helix",
            "avmnite-02h",
            "I.I.I.I",
            "alpha-ent"
        ],
        "connections": [
            "I.I.I.I",
            "global-pharm"
        ],
        "freeRam": 32,
        "numberOfGrowthThreadsNeededToMax": 25477,
        "numberOfGrowthThreadsNeededToMaxHomeComputer": 23979,
        "growthMs": 618803,
        "weakenMs": 773504
    },
    {
        "hostname": "global-pharm",
        "ip": "89.2.5.9",
        "sshPortOpen": false,
        "ftpPortOpen": false,
        "smtpPortOpen": false,
        "httpPortOpen": false,
        "sqlPortOpen": false,
        "hasAdminRights": false,
        "cpuCores": 1,
        "isConnectedTo": false,
        "ramUsed": 0,
        "maxRam": 64,
        "organizationName": "Global Pharmaceuticals",
        "purchasedByPlayer": false,
        "backdoorInstalled": false,
        "baseDifficulty": 83,
        "hackDifficulty": 83,
        "minDifficulty": 28,
        "moneyAvailable": 1136681091.75,
        "moneyMax": 4262554094.0625,
        "numOpenPortsRequired": 4,
        "openPortCount": 0,
        "requiredHackingSkill": 846,
        "serverGrowth": 87,
        "path": [
            "n00dles",
            "zer0",
            "silver-helix",
            "avmnite-02h",
            "I.I.I.I",
            "alpha-ent",
            "global-pharm"
        ],
        "connections": [
            "alpha-ent",
            "unitalife"
        ],
        "freeRam": 64
    },
    {
        "hostname": "unitalife",
        "ip": "92.1.3.9",
        "sshPortOpen": false,
        "ftpPortOpen": false,
        "smtpPortOpen": false,
        "httpPortOpen": false,
        "sqlPortOpen": false,
        "hasAdminRights": false,
        "cpuCores": 1,
        "isConnectedTo": false,
        "ramUsed": 0,
        "maxRam": 16,
        "organizationName": "UnitaLife Group",
        "purchasedByPlayer": false,
        "backdoorInstalled": false,
        "baseDifficulty": 77,
        "hackDifficulty": 77,
        "minDifficulty": 26,
        "moneyAvailable": 752401923.75,
        "moneyMax": 2821507214.0625,
        "numOpenPortsRequired": 4,
        "openPortCount": 0,
        "requiredHackingSkill": 817,
        "serverGrowth": 77,
        "path": [
            "n00dles",
            "zer0",
            "silver-helix",
            "avmnite-02h",
            "I.I.I.I",
            "alpha-ent",
            "global-pharm",
            "unitalife"
        ],
        "connections": [
            "global-pharm"
        ],
        "freeRam": 16
    },
    {
        "hostname": "syscore",
        "ip": "51.0.0.0",
        "sshPortOpen": true,
        "ftpPortOpen": true,
        "smtpPortOpen": true,
        "httpPortOpen": true,
        "sqlPortOpen": false,
        "hasAdminRights": true,
        "cpuCores": 1,
        "isConnectedTo": false,
        "ramUsed": 0,
        "maxRam": 0,
        "organizationName": "SysCore Securities",
        "purchasedByPlayer": false,
        "backdoorInstalled": false,
        "baseDifficulty": 67,
        "hackDifficulty": 34.449999999999996,
        "minDifficulty": 22,
        "moneyAvailable": 0,
        "moneyMax": 1444179639.375,
        "numOpenPortsRequired": 4,
        "openPortCount": 4,
        "requiredHackingSkill": 571,
        "serverGrowth": 61,
        "path": [
            "n00dles",
            "zer0",
            "silver-helix",
            "avmnite-02h",
            "syscore"
        ],
        "connections": [
            "avmnite-02h",
            "aevum-police"
        ],
        "freeRam": 0,
        "numberOfGrowthThreadsNeededToMax": 27394,
        "numberOfGrowthThreadsNeededToMaxHomeComputer": 25783,
        "growthMs": 776400,
        "weakenMs": 970500
    },
    {
        "hostname": "aevum-police",
        "ip": "76.8.7.2",
        "sshPortOpen": true,
        "ftpPortOpen": true,
        "smtpPortOpen": true,
        "httpPortOpen": true,
        "sqlPortOpen": false,
        "hasAdminRights": true,
        "cpuCores": 1,
        "isConnectedTo": false,
        "ramUsed": 0,
        "maxRam": 32,
        "organizationName": "Aevum Police Headquarters",
        "purchasedByPlayer": false,
        "backdoorInstalled": false,
        "baseDifficulty": 74,
        "hackDifficulty": 31.592000000000002,
        "minDifficulty": 25,
        "moneyAvailable": 784653046.875,
        "moneyMax": 784653046.875,
        "numOpenPortsRequired": 4,
        "openPortCount": 4,
        "requiredHackingSkill": 406,
        "serverGrowth": 49,
        "path": [
            "n00dles",
            "zer0",
            "silver-helix",
            "avmnite-02h",
            "syscore",
            "aevum-police"
        ],
        "connections": [
            "syscore"
        ],
        "freeRam": 32,
        "hackThreadsForAllMoney": 1907,
        "hackChance": 0.5832466079999999,
        "hackMs": 159053,
        "numberOfGrowthThreadsNeededToMax": 0,
        "numberOfGrowthThreadsNeededToMaxHomeComputer": 0,
        "growthMs": 508967,
        "weakenMs": 636209
    },
    {
        "hostname": "crush-fitness",
        "ip": "39.4.3.4",
        "sshPortOpen": true,
        "ftpPortOpen": true,
        "smtpPortOpen": false,
        "httpPortOpen": false,
        "sqlPortOpen": false,
        "hasAdminRights": true,
        "cpuCores": 1,
        "isConnectedTo": false,
        "ramUsed": 0,
        "maxRam": 0,
        "organizationName": "Crush Fitness",
        "purchasedByPlayer": false,
        "backdoorInstalled": false,
        "baseDifficulty": 36,
        "hackDifficulty": 13.834,
        "minDifficulty": 12,
        "moneyAvailable": 0,
        "moneyMax": 123329595.9375,
        "numOpenPortsRequired": 2,
        "openPortCount": 2,
        "requiredHackingSkill": 225,
        "serverGrowth": 30,
        "path": [
            "n00dles",
            "zer0",
            "silver-helix",
            "crush-fitness"
        ],
        "connections": [
            "silver-helix"
        ],
        "freeRam": 0,
        "numberOfGrowthThreadsNeededToMax": 19772,
        "numberOfGrowthThreadsNeededToMaxHomeComputer": 18609,
        "growthMs": 129433,
        "weakenMs": 161791
    },
    {
        "hostname": "the-hub",
        "ip": "6.9.0.7",
        "sshPortOpen": true,
        "ftpPortOpen": true,
        "smtpPortOpen": false,
        "httpPortOpen": false,
        "sqlPortOpen": false,
        "hasAdminRights": true,
        "cpuCores": 1,
        "isConnectedTo": false,
        "ramUsed": 0,
        "maxRam": 16,
        "organizationName": "The Hub",
        "purchasedByPlayer": false,
        "backdoorInstalled": false,
        "baseDifficulty": 44,
        "hackDifficulty": 17.23,
        "minDifficulty": 15,
        "moneyAvailable": 0,
        "moneyMax": 466982426.25,
        "numOpenPortsRequired": 2,
        "openPortCount": 2,
        "requiredHackingSkill": 294,
        "serverGrowth": 45,
        "path": [
            "n00dles",
            "zer0",
            "silver-helix",
            "the-hub"
        ],
        "connections": [
            "silver-helix",
            "rothman-uni"
        ],
        "freeRam": 16,
        "numberOfGrowthThreadsNeededToMax": 17586,
        "numberOfGrowthThreadsNeededToMaxHomeComputer": 16552,
        "growthMs": 205739,
        "weakenMs": 257174
    },
    {
        "hostname": "rothman-uni",
        "ip": "9.8.1.7",
        "sshPortOpen": true,
        "ftpPortOpen": true,
        "smtpPortOpen": true,
        "httpPortOpen": false,
        "sqlPortOpen": false,
        "hasAdminRights": true,
        "cpuCores": 1,
        "isConnectedTo": false,
        "ramUsed": 0,
        "maxRam": 16,
        "organizationName": "Rothman University",
        "purchasedByPlayer": false,
        "backdoorInstalled": false,
        "baseDifficulty": 45,
        "hackDifficulty": 51.68,
        "minDifficulty": 15,
        "moneyAvailable": 642443087.8125,
        "moneyMax": 642443087.8125,
        "numOpenPortsRequired": 3,
        "openPortCount": 3,
        "requiredHackingSkill": 424,
        "serverGrowth": 42,
        "path": [
            "n00dles",
            "zer0",
            "silver-helix",
            "the-hub",
            "rothman-uni"
        ],
        "connections": [
            "the-hub",
            "lexo-corp",
            "rho-construction"
        ],
        "freeRam": 16,
        "hackThreadsForAllMoney": 2877,
        "hackChance": 0.40284384,
        "hackMs": 269992,
        "numberOfGrowthThreadsNeededToMax": 0,
        "numberOfGrowthThreadsNeededToMaxHomeComputer": 0,
        "growthMs": 863975,
        "weakenMs": 1079968
    },
    {
        "hostname": "rho-construction",
        "ip": "94.8.0.3",
        "sshPortOpen": true,
        "ftpPortOpen": true,
        "smtpPortOpen": true,
        "httpPortOpen": true,
        "sqlPortOpen": false,
        "hasAdminRights": true,
        "cpuCores": 1,
        "isConnectedTo": false,
        "ramUsed": 0,
        "maxRam": 16,
        "organizationName": "Rho Construction",
        "purchasedByPlayer": false,
        "backdoorInstalled": false,
        "baseDifficulty": 55,
        "hackDifficulty": 86.744,
        "minDifficulty": 18,
        "moneyAvailable": 133814430.99561518,
        "moneyMax": 1552942794.375,
        "numOpenPortsRequired": 3,
        "openPortCount": 4,
        "requiredHackingSkill": 505,
        "serverGrowth": 51,
        "path": [
            "n00dles",
            "zer0",
            "silver-helix",
            "the-hub",
            "rothman-uni",
            "rho-construction"
        ],
        "connections": [
            "rothman-uni",
            "galactic-cyber"
        ],
        "freeRam": 16,
        "hackThreadsForAllMoney": 14909,
        "hackChance": 0.09924104400000001,
        "hackMs": 537311,
        "numberOfGrowthThreadsNeededToMax": 9587,
        "numberOfGrowthThreadsNeededToMaxHomeComputer": 9023,
        "growthMs": 1719395,
        "weakenMs": 2149244
    },
    {
        "hostname": "galactic-cyber",
        "ip": "42.1.0.8",
        "sshPortOpen": false,
        "ftpPortOpen": false,
        "smtpPortOpen": false,
        "httpPortOpen": false,
        "sqlPortOpen": false,
        "hasAdminRights": false,
        "cpuCores": 1,
        "isConnectedTo": false,
        "ramUsed": 0,
        "maxRam": 0,
        "organizationName": "Galactic Cybersystems",
        "purchasedByPlayer": false,
        "backdoorInstalled": false,
        "baseDifficulty": 65,
        "hackDifficulty": 65,
        "minDifficulty": 22,
        "moneyAvailable": 602215447.5,
        "moneyMax": 2258307928.125,
        "numOpenPortsRequired": 5,
        "openPortCount": 0,
        "requiredHackingSkill": 864,
        "serverGrowth": 78,
        "path": [
            "n00dles",
            "zer0",
            "silver-helix",
            "the-hub",
            "rothman-uni",
            "rho-construction",
            "galactic-cyber"
        ],
        "connections": [
            "rho-construction"
        ],
        "freeRam": 0
    },
    {
        "hostname": "lexo-corp",
        "ip": "42.6.8.2",
        "sshPortOpen": true,
        "ftpPortOpen": true,
        "smtpPortOpen": true,
        "httpPortOpen": true,
        "sqlPortOpen": false,
        "hasAdminRights": true,
        "cpuCores": 1,
        "isConnectedTo": false,
        "ramUsed": 0,
        "maxRam": 64,
        "organizationName": "LexoCorp",
        "purchasedByPlayer": false,
        "backdoorInstalled": false,
        "baseDifficulty": 70,
        "hackDifficulty": 52.194,
        "minDifficulty": 23,
        "moneyAvailable": 0,
        "moneyMax": 2163378375,
        "numOpenPortsRequired": 4,
        "openPortCount": 4,
        "requiredHackingSkill": 653,
        "serverGrowth": 55,
        "path": [
            "n00dles",
            "zer0",
            "silver-helix",
            "the-hub",
            "rothman-uni",
            "lexo-corp"
        ],
        "connections": [
            "rothman-uni",
            "snap-fitness"
        ],
        "freeRam": 64,
        "numberOfGrowthThreadsNeededToMax": 46907,
        "numberOfGrowthThreadsNeededToMaxHomeComputer": 44147,
        "growthMs": 1339496,
        "weakenMs": 1674370
    },
    {
        "hostname": "snap-fitness",
        "ip": "20.8.9.0",
        "sshPortOpen": false,
        "ftpPortOpen": false,
        "smtpPortOpen": false,
        "httpPortOpen": false,
        "sqlPortOpen": false,
        "hasAdminRights": false,
        "cpuCores": 1,
        "isConnectedTo": false,
        "ramUsed": 0,
        "maxRam": 0,
        "organizationName": "Snap Fitness",
        "purchasedByPlayer": false,
        "backdoorInstalled": false,
        "baseDifficulty": 42,
        "hackDifficulty": 42,
        "minDifficulty": 14,
        "moneyAvailable": 337500000,
        "moneyMax": 1265625000,
        "numOpenPortsRequired": 4,
        "openPortCount": 0,
        "requiredHackingSkill": 768,
        "serverGrowth": 48,
        "path": [
            "n00dles",
            "zer0",
            "silver-helix",
            "the-hub",
            "rothman-uni",
            "lexo-corp",
            "snap-fitness"
        ],
        "connections": [
            "lexo-corp",
            "omnia"
        ],
        "freeRam": 0
    },
    {
        "hostname": "omnia",
        "ip": "76.1.3.4",
        "sshPortOpen": false,
        "ftpPortOpen": false,
        "smtpPortOpen": false,
        "httpPortOpen": false,
        "sqlPortOpen": false,
        "hasAdminRights": false,
        "cpuCores": 1,
        "isConnectedTo": false,
        "ramUsed": 0,
        "maxRam": 64,
        "organizationName": "Omnia Cybersystems",
        "purchasedByPlayer": false,
        "backdoorInstalled": false,
        "baseDifficulty": 92,
        "hackDifficulty": 92,
        "minDifficulty": 31,
        "moneyAvailable": 739225671.75,
        "moneyMax": 2772096269.0625,
        "numOpenPortsRequired": 5,
        "openPortCount": 0,
        "requiredHackingSkill": 920,
        "serverGrowth": 69,
        "path": [
            "n00dles",
            "zer0",
            "silver-helix",
            "the-hub",
            "rothman-uni",
            "lexo-corp",
            "snap-fitness",
            "omnia"
        ],
        "connections": [
            "snap-fitness",
            "icarus"
        ],
        "freeRam": 64
    },
    {
        "hostname": "icarus",
        "ip": "64.7.6.9",
        "sshPortOpen": false,
        "ftpPortOpen": false,
        "smtpPortOpen": false,
        "httpPortOpen": false,
        "sqlPortOpen": false,
        "hasAdminRights": false,
        "cpuCores": 1,
        "isConnectedTo": false,
        "ramUsed": 0,
        "maxRam": 0,
        "organizationName": "Icarus Microsystems",
        "purchasedByPlayer": false,
        "backdoorInstalled": false,
        "baseDifficulty": 88,
        "hackDifficulty": 88,
        "minDifficulty": 29,
        "moneyAvailable": 712399907.25,
        "moneyMax": 2671499652.1875,
        "numOpenPortsRequired": 5,
        "openPortCount": 0,
        "requiredHackingSkill": 859,
        "serverGrowth": 95,
        "path": [
            "n00dles",
            "zer0",
            "silver-helix",
            "the-hub",
            "rothman-uni",
            "lexo-corp",
            "snap-fitness",
            "omnia",
            "icarus"
        ],
        "connections": [
            "omnia",
            "infocomm"
        ],
        "freeRam": 0
    },
    {
        "hostname": "infocomm",
        "ip": "92.9.3.6",
        "sshPortOpen": false,
        "ftpPortOpen": false,
        "smtpPortOpen": false,
        "httpPortOpen": false,
        "sqlPortOpen": false,
        "hasAdminRights": false,
        "cpuCores": 1,
        "isConnectedTo": false,
        "ramUsed": 0,
        "maxRam": 0,
        "organizationName": "InfoComm",
        "purchasedByPlayer": false,
        "backdoorInstalled": false,
        "baseDifficulty": 83,
        "hackDifficulty": 83,
        "minDifficulty": 28,
        "moneyAvailable": 660938170.5,
        "moneyMax": 2478518139.375,
        "numOpenPortsRequired": 5,
        "openPortCount": 0,
        "requiredHackingSkill": 905,
        "serverGrowth": 70,
        "path": [
            "n00dles",
            "zer0",
            "silver-helix",
            "the-hub",
            "rothman-uni",
            "lexo-corp",
            "snap-fitness",
            "omnia",
            "icarus",
            "infocomm"
        ],
        "connections": [
            "icarus",
            "applied-energetics",
            "run4theh111z"
        ],
        "freeRam": 0
    },
    {
        "hostname": "run4theh111z",
        "ip": "40.3.0.5",
        "sshPortOpen": true,
        "ftpPortOpen": true,
        "smtpPortOpen": true,
        "httpPortOpen": true,
        "sqlPortOpen": false,
        "hasAdminRights": true,
        "cpuCores": 1,
        "isConnectedTo": false,
        "ramUsed": 0,
        "maxRam": 256,
        "organizationName": "The Runners",
        "purchasedByPlayer": false,
        "backdoorInstalled": true,
        "baseDifficulty": 1,
        "hackDifficulty": 1,
        "minDifficulty": 1,
        "moneyAvailable": 0,
        "moneyMax": 0,
        "numOpenPortsRequired": 4,
        "openPortCount": 4,
        "requiredHackingSkill": 535,
        "serverGrowth": 1,
        "path": [
            "n00dles",
            "zer0",
            "silver-helix",
            "the-hub",
            "rothman-uni",
            "lexo-corp",
            "snap-fitness",
            "omnia",
            "icarus",
            "infocomm",
            "run4theh111z"
        ],
        "connections": [
            "infocomm",
            "fulcrumtech",
            "helios"
        ],
        "freeRam": 256
    },
    {
        "hostname": "helios",
        "ip": "44.2.5.4",
        "sshPortOpen": false,
        "ftpPortOpen": false,
        "smtpPortOpen": false,
        "httpPortOpen": false,
        "sqlPortOpen": false,
        "hasAdminRights": false,
        "cpuCores": 1,
        "isConnectedTo": false,
        "ramUsed": 0,
        "maxRam": 128,
        "organizationName": "Helios Labs",
        "purchasedByPlayer": false,
        "backdoorInstalled": false,
        "baseDifficulty": 93,
        "hackDifficulty": 93,
        "minDifficulty": 31,
        "moneyAvailable": 413854914.75,
        "moneyMax": 1551955930.3125,
        "numOpenPortsRequired": 5,
        "openPortCount": 0,
        "requiredHackingSkill": 875,
        "serverGrowth": 78,
        "path": [
            "n00dles",
            "zer0",
            "silver-helix",
            "the-hub",
            "rothman-uni",
            "lexo-corp",
            "snap-fitness",
            "omnia",
            "icarus",
            "infocomm",
            "run4theh111z",
            "helios"
        ],
        "connections": [
            "run4theh111z"
        ],
        "freeRam": 128
    },
    {
        "hostname": "fulcrumtech",
        "ip": "84.7.2.7",
        "sshPortOpen": false,
        "ftpPortOpen": false,
        "smtpPortOpen": false,
        "httpPortOpen": false,
        "sqlPortOpen": false,
        "hasAdminRights": false,
        "cpuCores": 1,
        "isConnectedTo": false,
        "ramUsed": 0,
        "maxRam": 128,
        "organizationName": "Fulcrum Technologies",
        "purchasedByPlayer": false,
        "backdoorInstalled": false,
        "baseDifficulty": 95,
        "hackDifficulty": 95,
        "minDifficulty": 32,
        "moneyAvailable": 1198010721,
        "moneyMax": 4492540203.75,
        "numOpenPortsRequired": 5,
        "openPortCount": 0,
        "requiredHackingSkill": 1076,
        "serverGrowth": 80,
        "path": [
            "n00dles",
            "zer0",
            "silver-helix",
            "the-hub",
            "rothman-uni",
            "lexo-corp",
            "snap-fitness",
            "omnia",
            "icarus",
            "infocomm",
            "run4theh111z",
            "fulcrumtech"
        ],
        "connections": [
            "run4theh111z"
        ],
        "freeRam": 128
    },
    {
        "hostname": "applied-energetics",
        "ip": "90.0.5.5",
        "sshPortOpen": false,
        "ftpPortOpen": false,
        "smtpPortOpen": false,
        "httpPortOpen": false,
        "sqlPortOpen": false,
        "hasAdminRights": false,
        "cpuCores": 1,
        "isConnectedTo": false,
        "ramUsed": 0,
        "maxRam": 0,
        "organizationName": "Applied Energetics",
        "purchasedByPlayer": false,
        "backdoorInstalled": false,
        "baseDifficulty": 65,
        "hackDifficulty": 65,
        "minDifficulty": 22,
        "moneyAvailable": 543594866.25,
        "moneyMax": 2038480748.4375,
        "numOpenPortsRequired": 4,
        "openPortCount": 0,
        "requiredHackingSkill": 830,
        "serverGrowth": 74,
        "path": [
            "n00dles",
            "zer0",
            "silver-helix",
            "the-hub",
            "rothman-uni",
            "lexo-corp",
            "snap-fitness",
            "omnia",
            "icarus",
            "infocomm",
            "applied-energetics"
        ],
        "connections": [
            "infocomm",
            "vitalife"
        ],
        "freeRam": 0
    },
    {
        "hostname": "vitalife",
        "ip": "46.8.8.3",
        "sshPortOpen": false,
        "ftpPortOpen": false,
        "smtpPortOpen": false,
        "httpPortOpen": false,
        "sqlPortOpen": false,
        "hasAdminRights": false,
        "cpuCores": 1,
        "isConnectedTo": false,
        "ramUsed": 0,
        "maxRam": 128,
        "organizationName": "VitaLife",
        "purchasedByPlayer": false,
        "backdoorInstalled": false,
        "baseDifficulty": 83,
        "hackDifficulty": 83,
        "minDifficulty": 28,
        "moneyAvailable": 577507408.5,
        "moneyMax": 2165652781.875,
        "numOpenPortsRequired": 5,
        "openPortCount": 0,
        "requiredHackingSkill": 872,
        "serverGrowth": 60,
        "path": [
            "n00dles",
            "zer0",
            "silver-helix",
            "the-hub",
            "rothman-uni",
            "lexo-corp",
            "snap-fitness",
            "omnia",
            "icarus",
            "infocomm",
            "applied-energetics",
            "vitalife"
        ],
        "connections": [
            "applied-energetics",
            "4sigma"
        ],
        "freeRam": 128
    },
    {
        "hostname": "4sigma",
        "ip": "89.8.3.7",
        "sshPortOpen": false,
        "ftpPortOpen": false,
        "smtpPortOpen": false,
        "httpPortOpen": false,
        "sqlPortOpen": false,
        "hasAdminRights": false,
        "cpuCores": 1,
        "isConnectedTo": false,
        "ramUsed": 0,
        "maxRam": 0,
        "organizationName": "Four Sigma",
        "purchasedByPlayer": false,
        "backdoorInstalled": false,
        "baseDifficulty": 71,
        "hackDifficulty": 71,
        "minDifficulty": 24,
        "moneyAvailable": 13513288459.5,
        "moneyMax": 50674831723.125,
        "numOpenPortsRequired": 5,
        "openPortCount": 0,
        "requiredHackingSkill": 1029,
        "serverGrowth": 83,
        "path": [
            "n00dles",
            "zer0",
            "silver-helix",
            "the-hub",
            "rothman-uni",
            "lexo-corp",
            "snap-fitness",
            "omnia",
            "icarus",
            "infocomm",
            "applied-energetics",
            "vitalife",
            "4sigma"
        ],
        "connections": [
            "vitalife",
            "blade",
            "powerhouse-fitness"
        ],
        "freeRam": 0
    },
    {
        "hostname": "powerhouse-fitness",
        "ip": "76.5.1.2",
        "sshPortOpen": false,
        "ftpPortOpen": false,
        "smtpPortOpen": false,
        "httpPortOpen": false,
        "sqlPortOpen": false,
        "hasAdminRights": false,
        "cpuCores": 1,
        "isConnectedTo": false,
        "ramUsed": 0,
        "maxRam": 64,
        "organizationName": "Powerhouse Fitness",
        "purchasedByPlayer": false,
        "backdoorInstalled": false,
        "baseDifficulty": 60,
        "hackDifficulty": 60,
        "minDifficulty": 20,
        "moneyAvailable": 675000000,
        "moneyMax": 2531250000,
        "numOpenPortsRequired": 5,
        "openPortCount": 0,
        "requiredHackingSkill": 978,
        "serverGrowth": 55,
        "path": [
            "n00dles",
            "zer0",
            "silver-helix",
            "the-hub",
            "rothman-uni",
            "lexo-corp",
            "snap-fitness",
            "omnia",
            "icarus",
            "infocomm",
            "applied-energetics",
            "vitalife",
            "4sigma",
            "powerhouse-fitness"
        ],
        "connections": [
            "4sigma"
        ],
        "freeRam": 64
    },
    {
        "hostname": "blade",
        "ip": "79.0.8.2",
        "sshPortOpen": false,
        "ftpPortOpen": false,
        "smtpPortOpen": false,
        "httpPortOpen": false,
        "sqlPortOpen": false,
        "hasAdminRights": false,
        "cpuCores": 1,
        "isConnectedTo": false,
        "ramUsed": 0,
        "maxRam": 64,
        "organizationName": "Blade Industries",
        "purchasedByPlayer": false,
        "backdoorInstalled": false,
        "baseDifficulty": 95,
        "hackDifficulty": 95,
        "minDifficulty": 32,
        "moneyAvailable": 13339517040,
        "moneyMax": 50023188900,
        "numOpenPortsRequired": 5,
        "openPortCount": 0,
        "requiredHackingSkill": 908,
        "serverGrowth": 76,
        "path": [
            "n00dles",
            "zer0",
            "silver-helix",
            "the-hub",
            "rothman-uni",
            "lexo-corp",
            "snap-fitness",
            "omnia",
            "icarus",
            "infocomm",
            "applied-energetics",
            "vitalife",
            "4sigma",
            "blade"
        ],
        "connections": [
            "4sigma",
            "megacorp"
        ],
        "freeRam": 64
    },
    {
        "hostname": "megacorp",
        "ip": "45.0.5.0",
        "sshPortOpen": false,
        "ftpPortOpen": false,
        "smtpPortOpen": false,
        "httpPortOpen": false,
        "sqlPortOpen": false,
        "hasAdminRights": false,
        "cpuCores": 1,
        "isConnectedTo": false,
        "ramUsed": 0,
        "maxRam": 0,
        "organizationName": "MegaCorp",
        "purchasedByPlayer": false,
        "backdoorInstalled": false,
        "baseDifficulty": 99,
        "hackDifficulty": 99,
        "minDifficulty": 33,
        "moneyAvailable": 41376868971,
        "moneyMax": 155163258641.25,
        "numOpenPortsRequired": 5,
        "openPortCount": 0,
        "requiredHackingSkill": 1190,
        "serverGrowth": 99,
        "path": [
            "n00dles",
            "zer0",
            "silver-helix",
            "the-hub",
            "rothman-uni",
            "lexo-corp",
            "snap-fitness",
            "omnia",
            "icarus",
            "infocomm",
            "applied-energetics",
            "vitalife",
            "4sigma",
            "blade",
            "megacorp"
        ],
        "connections": [
            "blade"
        ],
        "freeRam": 0
    },
    {
        "hostname": "home",
        "ip": "26.4.2.1",
        "sshPortOpen": false,
        "ftpPortOpen": false,
        "smtpPortOpen": false,
        "httpPortOpen": false,
        "sqlPortOpen": false,
        "hasAdminRights": true,
        "cpuCores": 2,
        "isConnectedTo": true,
        "ramUsed": 4084.9,
        "maxRam": 4096,
        "organizationName": "Home PC",
        "purchasedByPlayer": true,
        "backdoorInstalled": false,
        "baseDifficulty": 1,
        "hackDifficulty": 1,
        "minDifficulty": 1,
        "moneyAvailable": 0,
        "moneyMax": 0,
        "numOpenPortsRequired": 5,
        "openPortCount": 0,
        "requiredHackingSkill": 1,
        "serverGrowth": 1,
        "path": [],
        "connections": [],
        "freeRam": 0.900000000000091
    }
]